Tyf/__init__.py
Tyf/decoders.py
Tyf/encoders.py
Tyf/gkd.py
Tyf/ifd.py
Tyf/tags.py
Tyf/tags.sqlite
Tyf/values.py
Tyf-1.5.1.dist-info/METADATA
Tyf-1.5.1.dist-info/WHEEL
Tyf-1.5.1.dist-info/top_level.txt
Tyf-1.5.1.dist-info/RECORD
