Metadata-Version: 2.1
Name: Tyf
Version: 1.5.1
Summary: Pythonic way to read and edit IFD and EXIF tags.
Home-page: https://github.com/Moustikitos/Tyf
Download-URL: https://github.com/Moustikitos/tyf/archive/master.zip
Author: Bruno THOORENS
Author-email: moustikitos@gmail.com
Maintainer: Bruno THOORENS
Maintainer-email: moustikitos@gmail.com
License: Copyright 2015-2020, THOORENS Bruno, BSD licence
Keywords: ifd,tiff,jpeg,exif,gps,geotiff,PIL,Pillow,xmp
Classifier: Development Status :: 6 - Mature
Classifier: Environment :: Console
Classifier: Intended Audience :: Developers
Classifier: Intended Audience :: Information Technology
Classifier: License :: OSI Approved :: BSD License
Classifier: Operating System :: OS Independent
Classifier: Programming Language :: Python
Classifier: Programming Language :: Python :: 2
Classifier: Programming Language :: Python :: 3
Classifier: Topic :: Multimedia :: Graphics
